libassist.cpython-313-darwin.so
assist/__init__.py
assist/ephem.py
assist/extras.py
assist/py.typed
assist_adam_fork-1.1.9.post1.dist-info/licenses/LICENSE
assist_adam_fork-1.1.9.post1.dist-info/METADATA
assist_adam_fork-1.1.9.post1.dist-info/WHEEL
assist_adam_fork-1.1.9.post1.dist-info/top_level.txt
assist_adam_fork-1.1.9.post1.dist-info/RECORD
