Metadata-Version: 2.4
Name: assist-adam-fork
Version: 1.1.9.post1
Summary: A temporary fork of ASSIST: A library high accuracy ephemeris in REBOUND
Home-page: https://github.com/matthewholman/assist
Author: Matthew Holman
Author-email: mholman@cfa.harvard.edu
License: GPL
Keywords: astronomy astrophysics nbody integrator
Classifier: Development Status :: 5 - Production/Stable
Classifier: Intended Audience :: Science/Research
Classifier: Intended Audience :: Developers
Classifier: Topic :: Software Development :: Build Tools
Classifier: Topic :: Scientific/Engineering :: Astronomy
Classifier: License :: OSI Approved :: GNU General Public License v3 or later (GPLv3+)
Classifier: Programming Language :: Python :: 3
License-File: LICENSE
Requires-Dist: rebound>=4.0.1
Requires-Dist: numpy
Dynamic: author
Dynamic: author-email
Dynamic: classifier
Dynamic: description
Dynamic: description-content-type
Dynamic: home-page
Dynamic: keywords
Dynamic: license
Dynamic: license-file
Dynamic: requires-dist
Dynamic: summary
